Metadata-Version: 2.4
Name: fellow
Version: 0.1.0
Summary: Fellow CLI tool is a command line development assistant
Author-email: Manuel Zierl <manuel.zierl@web.de>
License: MIT
Project-URL: Homepage, https://github.com/ManuelZierl/fellow
Project-URL: Source, https://github.com/ManuelZierl/fellow
Project-URL: Tracker, https://github.com/ManuelZierl/fellow/issues
Classifier: License :: OSI Approved :: MIT License
Classifier: Programming Language :: Python :: 3
Classifier: Programming Language :: Python :: 3.10
Classifier: Programming Language :: Python :: 3.11
Classifier: Typing :: Typed
Classifier: Development Status :: 4 - Beta
Classifier: Intended Audience :: Developers
Classifier: Intended Audience :: Information Technology
Classifier: Environment :: Console
Classifier: Topic :: Software Development :: Build Tools
Classifier: Topic :: Scientific/Engineering :: Artificial Intelligence
Classifier: Topic :: Software Development :: Libraries
Classifier: Operating System :: OS Independent
Requires-Python: >=3.10
License-File: LICENSE
Requires-Dist: httpx>=0.28.1
Requires-Dist: openai>=1.69.0
Requires-Dist: tiktoken>=0.9.0
Requires-Dist: pexpect>=4.9.0
Requires-Dist: pydantic~=2.11.0
Requires-Dist: PyYAML~=6.0.2
Requires-Dist: google-genai>=1.11.0
Dynamic: license-file
